{
  "$id": "https://schemas.dxcf.technology/Companies.schema.json",
  "$schema": "http://json-schema.org/draft-07/schema#",
  "description": "DXC Framework Companies data file",
  "type": "array",
  "items": {
    "$ref": "#/definitions/Company"
  },
  "definitions": {
    "Company": {
      "type": "object",
      "required": [ "Name", "Code" ],
      "properties": {
        "Name": {
          "type": "string",
          "description": "The Name of the Company.",
          "minLength": 2,
          "maxLength": 32,
          "pattern": "^([A-Z][a-z0-9]{0,31})*$"
        },
        "Code": {
          "type": "string",
          "description": "The Code of the Company.",
          "pattern": "^[a-z][a-z0-9]{0,3}$"
        },
        "Source": {
          "type": "string",
          "description": "The Source of the Company.",
          "enum": [ "Default", "System", "User" ]
        }
      },
      "additionalProperties": false
    }
  }
}
